TenshiTranslator/__init__.py
TenshiTranslator/Glossary/CSVGlossary.py
TenshiTranslator/Glossary/Glossary.py
TenshiTranslator/Glossary/PassthroughGlossary.py
TenshiTranslator/Glossary/__init__.py
TenshiTranslator/OutputFormat/EnglishOnlyFormat.py
TenshiTranslator/OutputFormat/LineByLineFormat.py
TenshiTranslator/OutputFormat/OutputFormat.py
TenshiTranslator/OutputFormat/__init__.py
TenshiTranslator/Translator/BatchTranslator.py
TenshiTranslator/Translator/OfflineTranslator.py
TenshiTranslator/Translator/OnlineTranslator.py
TenshiTranslator/Translator/Translator.py
TenshiTranslator/Translator/__init__.py
TenshiTranslator/Util/TextProcessor.py
TenshiTranslator/Util/__init__.py
tenshitranslator-2.0.0.dist-info/METADATA
tenshitranslator-2.0.0.dist-info/WHEEL
tenshitranslator-2.0.0.dist-info/licenses/LICENSE
tenshitranslator-2.0.0.dist-info/RECORD
