Metadata-Version: 2.3
Name: TenshiTranslator
Version: 2.0.0
Summary: Novel Translation utility using Sugoi Translator
Project-URL: Homepage, https://github.com/Ryan4253/TenshiTranslator
Project-URL: Issues, https://github.com/Ryan4253/TenshiTranslator/issues
Project-URL: documentation, https://ryan4253.github.io/TenshiTranslator/
Author-email: Ryan4253 <ryan.liao0305@gmail.com>
License:                     GNU GENERAL PUBLIC LICENSE
License-File: LICENSE
Classifier: Development Status :: 5 - Production/Stable
Classifier: Framework :: Pytest
Classifier: Framework :: Sphinx
Classifier: License :: OSI Approved :: GNU General Public License v3 or later (GPLv3+)
Classifier: Operating System :: Microsoft :: Windows
Classifier: Programming Language :: Python :: 3
Classifier: Topic :: Text Processing :: Linguistic
Requires-Python: >=3.10
Requires-Dist: chromedriver-autoinstaller
Requires-Dist: requests
Requires-Dist: selenium
